LICENSE
README.md
setup.py
dbgeomparser/__init__.py
dbgeomparser/custom_exceptions.py
dbgeomparser/oraclegeom.py
dbgeomparser.egg-info/PKG-INFO
dbgeomparser.egg-info/SOURCES.txt
dbgeomparser.egg-info/dependency_links.txt
dbgeomparser.egg-info/requires.txt
dbgeomparser.egg-info/top_level.txt