Metadata-Version: 2.1
Name: dbgeomparser
Version: 0.1.6
Summary: A package to handle conversion of shapely geometries to Oracle database compatible geometry objects
Home-page: https://github.com/massivebean22/dbgeomparser
Author: Nino Shaw
Classifier: Programming Language :: Python :: 3
Classifier: License :: OSI Approved :: MIT License
Classifier: Operating System :: OS Independent
Requires-Python: >=3.6
License-File: LICENSE
Requires-Dist: oracledb
Requires-Dist: shapely
Requires-Dist: numpy
